KorInput/__init__.py
KorInput/ktifpg.py
KoreanInput-1.0.dist-info/METADATA
KoreanInput-1.0.dist-info/WHEEL
KoreanInput-1.0.dist-info/top_level.txt
KoreanInput-1.0.dist-info/RECORD
